[
 {
   "id": 1,
   "Vous_avez_accédé_à_la_DFGSM2_par": "Redoublant de PACES"
 },
 {
   "id": 2,
   "Vous_avez_accédé_à_la_DFGSM2_par": ""
 },
 {
   "id": 3,
   "Vous_avez_accédé_à_la_DFGSM2_par": "Redoublant de PACES"
 },
 {
   "id": 4,
   "Vous_avez_accédé_à_la_DFGSM2_par": "Nouvelle-Calédonie / Luxembourg"
 },
 {
   "id": 5,
   "Vous_avez_accédé_à_la_DFGSM2_par": "Redoublant de PACES"
 },
 {
   "id": 6,
   "Vous_avez_accédé_à_la_DFGSM2_par": "Redoublant de PACES"
 },
 {
   "id": 7,
   "Vous_avez_accédé_à_la_DFGSM2_par": "Redoublant de PACES"
 },
 {
   "id": 8,
   "Vous_avez_accédé_à_la_DFGSM2_par": "Redoublant de PACES"
 },
 {
   "id": 9,
   "Vous_avez_accédé_à_la_DFGSM2_par": "Redoublant de PACES"
 },
 {
   "id": 10,
   "Vous_avez_accédé_à_la_DFGSM2_par": "PACES adaptée oral"
 },
 {
   "id": 11,
   "Vous_avez_accédé_à_la_DFGSM2_par": ""
 },
 {
   "id": 12,
   "Vous_avez_accédé_à_la_DFGSM2_par": "Redoublant de PACES"
 },
 {
   "id": 13,
   "Vous_avez_accédé_à_la_DFGSM2_par": "Primant de PACES"
 },
 {
   "id": 14,
   "Vous_avez_accédé_à_la_DFGSM2_par": "Primant de PACES"
 },
 {
   "id": 15,
   "Vous_avez_accédé_à_la_DFGSM2_par": "Primant de PACES"
 },
 {
   "id": 16,
   "Vous_avez_accédé_à_la_DFGSM2_par": "Redoublant de PACES"
 },
 {
   "id": 17,
   "Vous_avez_accédé_à_la_DFGSM2_par": "Redoublant de PACES"
 },
 {
   "id": 18,
   "Vous_avez_accédé_à_la_DFGSM2_par": ""
 },
 {
   "id": 19,
   "Vous_avez_accédé_à_la_DFGSM2_par": "Redoublant de PACES"
 },
 {
   "id": 20,
   "Vous_avez_accédé_à_la_DFGSM2_par": "Redoublant de PACES"
 },
 {
   "id": 21,
   "Vous_avez_accédé_à_la_DFGSM2_par": ""
 },
 {
   "id": 22,
   "Vous_avez_accédé_à_la_DFGSM2_par": ""
 },
 {
   "id": 23,
   "Vous_avez_accédé_à_la_DFGSM2_par": "Primant de PACES"
 },
 {
   "id": 24,
   "Vous_avez_accédé_à_la_DFGSM2_par": "Nouvelle-Calédonie / Luxembourg"
 },
 {
   "id": 25,
   "Vous_avez_accédé_à_la_DFGSM2_par": ""
 },
 {
   "id": 26,
   "Vous_avez_accédé_à_la_DFGSM2_par": "Redoublant de PACES"
 },
 {
   "id": 27,
   "Vous_avez_accédé_à_la_DFGSM2_par": "PACES adaptée écrit"
 },
 {
   "id": 28,
   "Vous_avez_accédé_à_la_DFGSM2_par": "Primant de PACES"
 },
 {
   "id": 29,
   "Vous_avez_accédé_à_la_DFGSM2_par": "Primant de PACES"
 },
 {
   "id": 30,
   "Vous_avez_accédé_à_la_DFGSM2_par": "Primant de PACES"
 },
 {
   "id": 31,
   "Vous_avez_accédé_à_la_DFGSM2_par": "PACES adaptée écrit"
 },
 {
   "id": 32,
   "Vous_avez_accédé_à_la_DFGSM2_par": "Redoublant de PACES"
 },
 {
   "id": 33,
   "Vous_avez_accédé_à_la_DFGSM2_par": "Primant de PACES"
 },
 {
   "id": 34,
   "Vous_avez_accédé_à_la_DFGSM2_par": "Primant de PACES"
 },
 {
   "id": 35,
   "Vous_avez_accédé_à_la_DFGSM2_par": "PACES adaptée oral"
 },
 {
   "id": 36,
   "Vous_avez_accédé_à_la_DFGSM2_par": ""
 },
 {
   "id": 37,
   "Vous_avez_accédé_à_la_DFGSM2_par": ""
 },
 {
   "id": 38,
   "Vous_avez_accédé_à_la_DFGSM2_par": ""
 },
 {
   "id": 39,
   "Vous_avez_accédé_à_la_DFGSM2_par": "Primant de PACES"
 },
 {
   "id": 40,
   "Vous_avez_accédé_à_la_DFGSM2_par": "Primant de PACES"
 },
 {
   "id": 41,
   "Vous_avez_accédé_à_la_DFGSM2_par": "Primant de PACES"
 },
 {
   "id": 42,
   "Vous_avez_accédé_à_la_DFGSM2_par": "Passerelle"
 },
 {
   "id": 43,
   "Vous_avez_accédé_à_la_DFGSM2_par": "Redoublant de PACES"
 },
 {
   "id": 44,
   "Vous_avez_accédé_à_la_DFGSM2_par": ""
 },
 {
   "id": 45,
   "Vous_avez_accédé_à_la_DFGSM2_par": "Primant de PACES"
 },
 {
   "id": 46,
   "Vous_avez_accédé_à_la_DFGSM2_par": ""
 },
 {
   "id": 47,
   "Vous_avez_accédé_à_la_DFGSM2_par": "Redoublant de PACES"
 },
 {
   "id": 48,
   "Vous_avez_accédé_à_la_DFGSM2_par": "Redoublant de PACES"
 },
 {
   "id": 49,
   "Vous_avez_accédé_à_la_DFGSM2_par": "Nouvelle-Calédonie / Luxembourg"
 },
 {
   "id": 50,
   "Vous_avez_accédé_à_la_DFGSM2_par": "Redoublant de PACES"
 },
 {
   "id": 51,
   "Vous_avez_accédé_à_la_DFGSM2_par": ""
 },
 {
   "id": 52,
   "Vous_avez_accédé_à_la_DFGSM2_par": "Primant de PACES"
 },
 {
   "id": 53,
   "Vous_avez_accédé_à_la_DFGSM2_par": "Redoublant de PACES"
 },
 {
   "id": 54,
   "Vous_avez_accédé_à_la_DFGSM2_par": "Primant de PACES"
 },
 {
   "id": 55,
   "Vous_avez_accédé_à_la_DFGSM2_par": "Redoublant de PACES"
 },
 {
   "id": 56,
   "Vous_avez_accédé_à_la_DFGSM2_par": "Primant de PACES"
 },
 {
   "id": 57,
   "Vous_avez_accédé_à_la_DFGSM2_par": ""
 },
 {
   "id": 58,
   "Vous_avez_accédé_à_la_DFGSM2_par": "Redoublant de PACES"
 },
 {
   "id": 59,
   "Vous_avez_accédé_à_la_DFGSM2_par": "Redoublant de PACES"
 },
 {
   "id": 60,
   "Vous_avez_accédé_à_la_DFGSM2_par": "Redoublant de PACES"
 },
 {
   "id": 61,
   "Vous_avez_accédé_à_la_DFGSM2_par": "Primant de PACES"
 },
 {
   "id": 62,
   "Vous_avez_accédé_à_la_DFGSM2_par": "Redoublant de PACES"
 },
 {
   "id": 63,
   "Vous_avez_accédé_à_la_DFGSM2_par": "Passerelle"
 },
 {
   "id": 64,
   "Vous_avez_accédé_à_la_DFGSM2_par": "PACES adaptée oral"
 },
 {
   "id": 65,
   "Vous_avez_accédé_à_la_DFGSM2_par": "Redoublant de PACES"
 },
 {
   "id": 66,
   "Vous_avez_accédé_à_la_DFGSM2_par": ""
 },
 {
   "id": 67,
   "Vous_avez_accédé_à_la_DFGSM2_par": "Redoublant de PACES"
 },
 {
   "id": 68,
   "Vous_avez_accédé_à_la_DFGSM2_par": "Primant de PACES"
 },
 {
   "id": 69,
   "Vous_avez_accédé_à_la_DFGSM2_par": "Primant de PACES"
 },
 {
   "id": 70,
   "Vous_avez_accédé_à_la_DFGSM2_par": "Redoublant de PACES"
 },
 {
   "id": 71,
   "Vous_avez_accédé_à_la_DFGSM2_par": ""
 },
 {
   "id": 72,
   "Vous_avez_accédé_à_la_DFGSM2_par": "Redoublant de PACES"
 },
 {
   "id": 73,
   "Vous_avez_accédé_à_la_DFGSM2_par": "Redoublant de PACES"
 },
 {
   "id": 74,
   "Vous_avez_accédé_à_la_DFGSM2_par": ""
 },
 {
   "id": 75,
   "Vous_avez_accédé_à_la_DFGSM2_par": "Redoublant de PACES"
 },
 {
   "id": 76,
   "Vous_avez_accédé_à_la_DFGSM2_par": "Redoublant de PACES"
 },
 {
   "id": 77,
   "Vous_avez_accédé_à_la_DFGSM2_par": "Redoublant de PACES"
 },
 {
   "id": 78,
   "Vous_avez_accédé_à_la_DFGSM2_par": "Primant de PACES"
 },
 {
   "id": 79,
   "Vous_avez_accédé_à_la_DFGSM2_par": "Redoublant de PACES"
 },
 {
   "id": 80,
   "Vous_avez_accédé_à_la_DFGSM2_par": "Primant de PACES"
 },
 {
   "id": 81,
   "Vous_avez_accédé_à_la_DFGSM2_par": "Primant de PACES"
 },
 {
   "id": 82,
   "Vous_avez_accédé_à_la_DFGSM2_par": "Redoublant de PACES"
 },
 {
   "id": 83,
   "Vous_avez_accédé_à_la_DFGSM2_par": "Redoublant de PACES"
 },
 {
   "id": 84,
   "Vous_avez_accédé_à_la_DFGSM2_par": ""
 },
 {
   "id": 85,
   "Vous_avez_accédé_à_la_DFGSM2_par": ""
 },
 {
   "id": 86,
   "Vous_avez_accédé_à_la_DFGSM2_par": "Redoublant de PACES"
 },
 {
   "id": 87,
   "Vous_avez_accédé_à_la_DFGSM2_par": "Primant de PACES"
 },
 {
   "id": 88,
   "Vous_avez_accédé_à_la_DFGSM2_par": "Primant de PACES"
 },
 {
   "id": 89,
   "Vous_avez_accédé_à_la_DFGSM2_par": ""
 },
 {
   "id": 90,
   "Vous_avez_accédé_à_la_DFGSM2_par": "Primant de PACES"
 },
 {
   "id": 91,
   "Vous_avez_accédé_à_la_DFGSM2_par": ""
 },
 {
   "id": 92,
   "Vous_avez_accédé_à_la_DFGSM2_par": "Nouvelle-Calédonie / Luxembourg"
 },
 {
   "id": 93,
   "Vous_avez_accédé_à_la_DFGSM2_par": "Nouvelle-Calédonie / Luxembourg"
 },
 {
   "id": 94,
   "Vous_avez_accédé_à_la_DFGSM2_par": "Redoublant de PACES"
 },
 {
   "id": 95,
   "Vous_avez_accédé_à_la_DFGSM2_par": "Redoublant de PACES"
 },
 {
   "id": 96,
   "Vous_avez_accédé_à_la_DFGSM2_par": "Primant de PACES"
 },
 {
   "id": 97,
   "Vous_avez_accédé_à_la_DFGSM2_par": "PACES adaptée écrit"
 },
 {
   "id": 98,
   "Vous_avez_accédé_à_la_DFGSM2_par": "Primant de PACES"
 },
 {
   "id": 99,
   "Vous_avez_accédé_à_la_DFGSM2_par": "Passerelle"
 },
 {
   "id": 100,
   "Vous_avez_accédé_à_la_DFGSM2_par": "PACES adaptée écrit"
 },
 {
   "id": 101,
   "Vous_avez_accédé_à_la_DFGSM2_par": "Redoublant de PACES"
 },
 {
   "id": 102,
   "Vous_avez_accédé_à_la_DFGSM2_par": "Primant de PACES"
 },
 {
   "id": 103,
   "Vous_avez_accédé_à_la_DFGSM2_par": "Redoublant de PACES"
 },
 {
   "id": 104,
   "Vous_avez_accédé_à_la_DFGSM2_par": "Redoublant de PACES"
 },
 {
   "id": 105,
   "Vous_avez_accédé_à_la_DFGSM2_par": "Primant de PACES"
 },
 {
   "id": 106,
   "Vous_avez_accédé_à_la_DFGSM2_par": "Primant de PACES"
 },
 {
   "id": 107,
   "Vous_avez_accédé_à_la_DFGSM2_par": "Primant de PACES"
 },
 {
   "id": 108,
   "Vous_avez_accédé_à_la_DFGSM2_par": "Primant de PACES"
 },
 {
   "id": 109,
   "Vous_avez_accédé_à_la_DFGSM2_par": "PACES adaptée écrit"
 },
 {
   "id": 110,
   "Vous_avez_accédé_à_la_DFGSM2_par": ""
 },
 {
   "id": 111,
   "Vous_avez_accédé_à_la_DFGSM2_par": "Redoublant de PACES"
 },
 {
   "id": 112,
   "Vous_avez_accédé_à_la_DFGSM2_par": ""
 },
 {
   "id": 113,
   "Vous_avez_accédé_à_la_DFGSM2_par": "Redoublant de PACES"
 },
 {
   "id": 114,
   "Vous_avez_accédé_à_la_DFGSM2_par": "Redoublant de PACES"
 },
 {
   "id": 115,
   "Vous_avez_accédé_à_la_DFGSM2_par": "Primant de PACES"
 },
 {
   "id": 116,
   "Vous_avez_accédé_à_la_DFGSM2_par": ""
 },
 {
   "id": 117,
   "Vous_avez_accédé_à_la_DFGSM2_par": "Redoublant de PACES"
 },
 {
   "id": 118,
   "Vous_avez_accédé_à_la_DFGSM2_par": ""
 },
 {
   "id": 119,
   "Vous_avez_accédé_à_la_DFGSM2_par": ""
 },
 {
   "id": 120,
   "Vous_avez_accédé_à_la_DFGSM2_par": "Primant de PACES"
 },
 {
   "id": 121,
   "Vous_avez_accédé_à_la_DFGSM2_par": ""
 },
 {
   "id": 122,
   "Vous_avez_accédé_à_la_DFGSM2_par": ""
 },
 {
   "id": 123,
   "Vous_avez_accédé_à_la_DFGSM2_par": ""
 },
 {
   "id": 124,
   "Vous_avez_accédé_à_la_DFGSM2_par": "Primant de PACES"
 },
 {
   "id": 125,
   "Vous_avez_accédé_à_la_DFGSM2_par": "Primant de PACES"
 },
 {
   "id": 126,
   "Vous_avez_accédé_à_la_DFGSM2_par": "PACES adaptée écrit"
 },
 {
   "id": 127,
   "Vous_avez_accédé_à_la_DFGSM2_par": ""
 },
 {
   "id": 128,
   "Vous_avez_accédé_à_la_DFGSM2_par": ""
 },
 {
   "id": 129,
   "Vous_avez_accédé_à_la_DFGSM2_par": "Primant de PACES"
 },
 {
   "id": 130,
   "Vous_avez_accédé_à_la_DFGSM2_par": ""
 },
 {
   "id": 131,
   "Vous_avez_accédé_à_la_DFGSM2_par": "Primant de PACES"
 },
 {
   "id": 132,
   "Vous_avez_accédé_à_la_DFGSM2_par": "PACES adaptée écrit"
 },
 {
   "id": 133,
   "Vous_avez_accédé_à_la_DFGSM2_par": "Primant de PACES"
 },
 {
   "id": 134,
   "Vous_avez_accédé_à_la_DFGSM2_par": ""
 },
 {
   "id": 135,
   "Vous_avez_accédé_à_la_DFGSM2_par": "Redoublant de PACES"
 },
 {
   "id": 136,
   "Vous_avez_accédé_à_la_DFGSM2_par": ""
 },
 {
   "id": 137,
   "Vous_avez_accédé_à_la_DFGSM2_par": ""
 },
 {
   "id": 138,
   "Vous_avez_accédé_à_la_DFGSM2_par": ""
 },
 {
   "id": 139,
   "Vous_avez_accédé_à_la_DFGSM2_par": "Redoublant de PACES"
 },
 {
   "id": 140,
   "Vous_avez_accédé_à_la_DFGSM2_par": "Redoublant de PACES"
 },
 {
   "id": 141,
   "Vous_avez_accédé_à_la_DFGSM2_par": "Redoublant de PACES"
 },
 {
   "id": 142,
   "Vous_avez_accédé_à_la_DFGSM2_par": "Primant de PACES"
 },
 {
   "id": 143,
   "Vous_avez_accédé_à_la_DFGSM2_par": ""
 },
 {
   "id": 144,
   "Vous_avez_accédé_à_la_DFGSM2_par": "Primant de PACES"
 },
 {
   "id": 145,
   "Vous_avez_accédé_à_la_DFGSM2_par": "Redoublant de PACES"
 },
 {
   "id": 146,
   "Vous_avez_accédé_à_la_DFGSM2_par": "Redoublant de PACES"
 },
 {
   "id": 147,
   "Vous_avez_accédé_à_la_DFGSM2_par": ""
 },
 {
   "id": 148,
   "Vous_avez_accédé_à_la_DFGSM2_par": ""
 },
 {
   "id": 149,
   "Vous_avez_accédé_à_la_DFGSM2_par": "Redoublant de PACES"
 },
 {
   "id": 150,
   "Vous_avez_accédé_à_la_DFGSM2_par": "Redoublant de PACES"
 },
 {
   "id": 151,
   "Vous_avez_accédé_à_la_DFGSM2_par": "Primant de PACES"
 },
 {
   "id": 152,
   "Vous_avez_accédé_à_la_DFGSM2_par": "Primant de PACES"
 },
 {
   "id": 153,
   "Vous_avez_accédé_à_la_DFGSM2_par": "Redoublant de PACES"
 },
 {
   "id": 154,
   "Vous_avez_accédé_à_la_DFGSM2_par": "Redoublant de PACES"
 },
 {
   "id": 155,
   "Vous_avez_accédé_à_la_DFGSM2_par": "Redoublant de PACES"
 },
 {
   "id": 156,
   "Vous_avez_accédé_à_la_DFGSM2_par": ""
 },
 {
   "id": 157,
   "Vous_avez_accédé_à_la_DFGSM2_par": "Redoublant de PACES"
 },
 {
   "id": 158,
   "Vous_avez_accédé_à_la_DFGSM2_par": "Redoublant de PACES"
 },
 {
   "id": 159,
   "Vous_avez_accédé_à_la_DFGSM2_par": ""
 },
 {
   "id": 160,
   "Vous_avez_accédé_à_la_DFGSM2_par": "Primant de PACES"
 },
 {
   "id": 161,
   "Vous_avez_accédé_à_la_DFGSM2_par": "PACES adaptée écrit"
 },
 {
   "id": 162,
   "Vous_avez_accédé_à_la_DFGSM2_par": "Redoublant de PACES"
 },
 {
   "id": 163,
   "Vous_avez_accédé_à_la_DFGSM2_par": "Primant de PACES"
 },
 {
   "id": 164,
   "Vous_avez_accédé_à_la_DFGSM2_par": "PACES adaptée oral"
 },
 {
   "id": 165,
   "Vous_avez_accédé_à_la_DFGSM2_par": ""
 },
 {
   "id": 166,
   "Vous_avez_accédé_à_la_DFGSM2_par": ""
 },
 {
   "id": 167,
   "Vous_avez_accédé_à_la_DFGSM2_par": "Redoublant de PACES"
 },
 {
   "id": 168,
   "Vous_avez_accédé_à_la_DFGSM2_par": "Passerelle"
 },
 {
   "id": 169,
   "Vous_avez_accédé_à_la_DFGSM2_par": "Redoublant de PACES"
 },
 {
   "id": 170,
   "Vous_avez_accédé_à_la_DFGSM2_par": "Redoublant de PACES"
 },
 {
   "id": 171,
   "Vous_avez_accédé_à_la_DFGSM2_par": "Redoublant de PACES"
 },
 {
   "id": 172,
   "Vous_avez_accédé_à_la_DFGSM2_par": "Redoublant de PACES"
 },
 {
   "id": 173,
   "Vous_avez_accédé_à_la_DFGSM2_par": "PACES adaptée oral"
 },
 {
   "id": 174,
   "Vous_avez_accédé_à_la_DFGSM2_par": "Primant de PACES"
 },
 {
   "id": 175,
   "Vous_avez_accédé_à_la_DFGSM2_par": ""
 },
 {
   "id": 176,
   "Vous_avez_accédé_à_la_DFGSM2_par": "Primant de PACES"
 },
 {
   "id": 177,
   "Vous_avez_accédé_à_la_DFGSM2_par": "Nouvelle-Calédonie / Luxembourg"
 },
 {
   "id": 178,
   "Vous_avez_accédé_à_la_DFGSM2_par": "Passerelle"
 },
 {
   "id": 179,
   "Vous_avez_accédé_à_la_DFGSM2_par": "PACES adaptée oral"
 },
 {
   "id": 180,
   "Vous_avez_accédé_à_la_DFGSM2_par": "Primant de PACES"
 },
 {
   "id": 181,
   "Vous_avez_accédé_à_la_DFGSM2_par": "Redoublant de PACES"
 },
 {
   "id": 182,
   "Vous_avez_accédé_à_la_DFGSM2_par": "Primant de PACES"
 },
 {
   "id": 183,
   "Vous_avez_accédé_à_la_DFGSM2_par": ""
 },
 {
   "id": 184,
   "Vous_avez_accédé_à_la_DFGSM2_par": "Primant de PACES"
 },
 {
   "id": 185,
   "Vous_avez_accédé_à_la_DFGSM2_par": "Redoublant de PACES"
 },
 {
   "id": 186,
   "Vous_avez_accédé_à_la_DFGSM2_par": "Redoublant de PACES"
 },
 {
   "id": 187,
   "Vous_avez_accédé_à_la_DFGSM2_par": ""
 },
 {
   "id": 188,
   "Vous_avez_accédé_à_la_DFGSM2_par": "Primant de PACES"
 },
 {
   "id": 189,
   "Vous_avez_accédé_à_la_DFGSM2_par": "PACES adaptée écrit"
 },
 {
   "id": 190,
   "Vous_avez_accédé_à_la_DFGSM2_par": ""
 },
 {
   "id": 191,
   "Vous_avez_accédé_à_la_DFGSM2_par": "Redoublant de PACES"
 },
 {
   "id": 192,
   "Vous_avez_accédé_à_la_DFGSM2_par": "Primant de PACES"
 },
 {
   "id": 193,
   "Vous_avez_accédé_à_la_DFGSM2_par": "Redoublant de PACES"
 },
 {
   "id": 194,
   "Vous_avez_accédé_à_la_DFGSM2_par": ""
 },
 {
   "id": 195,
   "Vous_avez_accédé_à_la_DFGSM2_par": ""
 },
 {
   "id": 196,
   "Vous_avez_accédé_à_la_DFGSM2_par": "Primant de PACES"
 },
 {
   "id": 197,
   "Vous_avez_accédé_à_la_DFGSM2_par": "Redoublant de PACES"
 },
 {
   "id": 198,
   "Vous_avez_accédé_à_la_DFGSM2_par": "Redoublant de PACES"
 },
 {
   "id": 199,
   "Vous_avez_accédé_à_la_DFGSM2_par": ""
 },
 {
   "id": 200,
   "Vous_avez_accédé_à_la_DFGSM2_par": "Redoublant de PACES"
 },
 {
   "id": 201,
   "Vous_avez_accédé_à_la_DFGSM2_par": "Primant de PACES"
 },
 {
   "id": 202,
   "Vous_avez_accédé_à_la_DFGSM2_par": "Primant de PACES"
 },
 {
   "id": 203,
   "Vous_avez_accédé_à_la_DFGSM2_par": "Nouvelle-Calédonie / Luxembourg"
 },
 {
   "id": 204,
   "Vous_avez_accédé_à_la_DFGSM2_par": "Redoublant de PACES"
 },
 {
   "id": 205,
   "Vous_avez_accédé_à_la_DFGSM2_par": "Redoublant de PACES"
 },
 {
   "id": 206,
   "Vous_avez_accédé_à_la_DFGSM2_par": "Redoublant de PACES"
 },
 {
   "id": 207,
   "Vous_avez_accédé_à_la_DFGSM2_par": "Redoublant de PACES"
 },
 {
   "id": 208,
   "Vous_avez_accédé_à_la_DFGSM2_par": "Redoublant de PACES"
 },
 {
   "id": 209,
   "Vous_avez_accédé_à_la_DFGSM2_par": ""
 },
 {
   "id": 210,
   "Vous_avez_accédé_à_la_DFGSM2_par": ""
 },
 {
   "id": 211,
   "Vous_avez_accédé_à_la_DFGSM2_par": "Primant de PACES"
 },
 {
   "id": 212,
   "Vous_avez_accédé_à_la_DFGSM2_par": "Redoublant de PACES"
 },
 {
   "id": 213,
   "Vous_avez_accédé_à_la_DFGSM2_par": "Primant de PACES"
 },
 {
   "id": 214,
   "Vous_avez_accédé_à_la_DFGSM2_par": "Primant de PACES"
 },
 {
   "id": 215,
   "Vous_avez_accédé_à_la_DFGSM2_par": ""
 },
 {
   "id": 216,
   "Vous_avez_accédé_à_la_DFGSM2_par": ""
 },
 {
   "id": 217,
   "Vous_avez_accédé_à_la_DFGSM2_par": ""
 },
 {
   "id": 218,
   "Vous_avez_accédé_à_la_DFGSM2_par": ""
 },
 {
   "id": 219,
   "Vous_avez_accédé_à_la_DFGSM2_par": "Redoublant de PACES"
 },
 {
   "id": 220,
   "Vous_avez_accédé_à_la_DFGSM2_par": ""
 },
 {
   "id": 221,
   "Vous_avez_accédé_à_la_DFGSM2_par": ""
 },
 {
   "id": 222,
   "Vous_avez_accédé_à_la_DFGSM2_par": "PACES adaptée oral"
 },
 {
   "id": 223,
   "Vous_avez_accédé_à_la_DFGSM2_par": "Redoublant de PACES"
 },
 {
   "id": 224,
   "Vous_avez_accédé_à_la_DFGSM2_par": "Primant de PACES"
 },
 {
   "id": 225,
   "Vous_avez_accédé_à_la_DFGSM2_par": "Redoublant de PACES"
 },
 {
   "id": 226,
   "Vous_avez_accédé_à_la_DFGSM2_par": ""
 },
 {
   "id": 227,
   "Vous_avez_accédé_à_la_DFGSM2_par": "PACES adaptée oral"
 },
 {
   "id": 228,
   "Vous_avez_accédé_à_la_DFGSM2_par": "Redoublant de PACES"
 },
 {
   "id": 229,
   "Vous_avez_accédé_à_la_DFGSM2_par": "Primant de PACES"
 },
 {
   "id": 230,
   "Vous_avez_accédé_à_la_DFGSM2_par": "Redoublant de PACES"
 },
 {
   "id": 231,
   "Vous_avez_accédé_à_la_DFGSM2_par": ""
 },
 {
   "id": 232,
   "Vous_avez_accédé_à_la_DFGSM2_par": "Redoublant de PACES"
 },
 {
   "id": 233,
   "Vous_avez_accédé_à_la_DFGSM2_par": "Passerelle"
 },
 {
   "id": 234,
   "Vous_avez_accédé_à_la_DFGSM2_par": "Redoublant de PACES"
 },
 {
   "id": 235,
   "Vous_avez_accédé_à_la_DFGSM2_par": "Redoublant de PACES"
 },
 {
   "id": 236,
   "Vous_avez_accédé_à_la_DFGSM2_par": "Redoublant de PACES"
 },
 {
   "id": 237,
   "Vous_avez_accédé_à_la_DFGSM2_par": ""
 },
 {
   "id": 238,
   "Vous_avez_accédé_à_la_DFGSM2_par": "Redoublant de PACES"
 },
 {
   "id": 239,
   "Vous_avez_accédé_à_la_DFGSM2_par": "Primant de PACES"
 },
 {
   "id": 240,
   "Vous_avez_accédé_à_la_DFGSM2_par": ""
 },
 {
   "id": 241,
   "Vous_avez_accédé_à_la_DFGSM2_par": "Redoublant de PACES"
 },
 {
   "id": 242,
   "Vous_avez_accédé_à_la_DFGSM2_par": "Redoublant de PACES"
 },
 {
   "id": 243,
   "Vous_avez_accédé_à_la_DFGSM2_par": "Primant de PACES"
 },
 {
   "id": 244,
   "Vous_avez_accédé_à_la_DFGSM2_par": "Primant de PACES"
 },
 {
   "id": 245,
   "Vous_avez_accédé_à_la_DFGSM2_par": "Primant de PACES"
 },
 {
   "id": 246,
   "Vous_avez_accédé_à_la_DFGSM2_par": "Redoublant de PACES"
 },
 {
   "id": 247,
   "Vous_avez_accédé_à_la_DFGSM2_par": "Primant de PACES"
 },
 {
   "id": 248,
   "Vous_avez_accédé_à_la_DFGSM2_par": "Primant de PACES"
 },
 {
   "id": 249,
   "Vous_avez_accédé_à_la_DFGSM2_par": "Redoublant de PACES"
 },
 {
   "id": 250,
   "Vous_avez_accédé_à_la_DFGSM2_par": "Redoublant de PACES"
 },
 {
   "id": 251,
   "Vous_avez_accédé_à_la_DFGSM2_par": ""
 },
 {
   "id": 252,
   "Vous_avez_accédé_à_la_DFGSM2_par": "Redoublant de PACES"
 },
 {
   "id": 253,
   "Vous_avez_accédé_à_la_DFGSM2_par": "PACES adaptée oral"
 },
 {
   "id": 254,
   "Vous_avez_accédé_à_la_DFGSM2_par": ""
 },
 {
   "id": 255,
   "Vous_avez_accédé_à_la_DFGSM2_par": "Primant de PACES"
 },
 {
   "id": 256,
   "Vous_avez_accédé_à_la_DFGSM2_par": "Redoublant de PACES"
 },
 {
   "id": 257,
   "Vous_avez_accédé_à_la_DFGSM2_par": "Primant de PACES"
 },
 {
   "id": 258,
   "Vous_avez_accédé_à_la_DFGSM2_par": "PACES adaptée écrit"
 },
 {
   "id": 259,
   "Vous_avez_accédé_à_la_DFGSM2_par": ""
 },
 {
   "id": 260,
   "Vous_avez_accédé_à_la_DFGSM2_par": "Primant de PACES"
 },
 {
   "id": 261,
   "Vous_avez_accédé_à_la_DFGSM2_par": "Primant de PACES"
 },
 {
   "id": 262,
   "Vous_avez_accédé_à_la_DFGSM2_par": "Primant de PACES"
 },
 {
   "id": 263,
   "Vous_avez_accédé_à_la_DFGSM2_par": "PACES adaptée écrit"
 },
 {
   "id": 264,
   "Vous_avez_accédé_à_la_DFGSM2_par": "Primant de PACES"
 },
 {
   "id": 265,
   "Vous_avez_accédé_à_la_DFGSM2_par": ""
 },
 {
   "id": 266,
   "Vous_avez_accédé_à_la_DFGSM2_par": "Redoublant de PACES"
 },
 {
   "id": 267,
   "Vous_avez_accédé_à_la_DFGSM2_par": "Primant de PACES"
 },
 {
   "id": 268,
   "Vous_avez_accédé_à_la_DFGSM2_par": "Redoublant de PACES"
 },
 {
   "id": 269,
   "Vous_avez_accédé_à_la_DFGSM2_par": "Redoublant de PACES"
 },
 {
   "id": 270,
   "Vous_avez_accédé_à_la_DFGSM2_par": "Redoublant de PACES"
 },
 {
   "id": 271,
   "Vous_avez_accédé_à_la_DFGSM2_par": "Redoublant de PACES"
 },
 {
   "id": 272,
   "Vous_avez_accédé_à_la_DFGSM2_par": "Passerelle"
 },
 {
   "id": 273,
   "Vous_avez_accédé_à_la_DFGSM2_par": "Redoublant de PACES"
 },
 {
   "id": 274,
   "Vous_avez_accédé_à_la_DFGSM2_par": "PACES adaptée écrit"
 },
 {
   "id": 275,
   "Vous_avez_accédé_à_la_DFGSM2_par": "Redoublant de PACES"
 },
 {
   "id": 276,
   "Vous_avez_accédé_à_la_DFGSM2_par": "Redoublant de PACES"
 },
 {
   "id": 277,
   "Vous_avez_accédé_à_la_DFGSM2_par": "Redoublant de PACES"
 },
 {
   "id": 278,
   "Vous_avez_accédé_à_la_DFGSM2_par": "Primant de PACES"
 },
 {
   "id": 279,
   "Vous_avez_accédé_à_la_DFGSM2_par": "Redoublant de PACES"
 },
 {
   "id": 280,
   "Vous_avez_accédé_à_la_DFGSM2_par": "Nouvelle-Calédonie / Luxembourg"
 },
 {
   "id": 281,
   "Vous_avez_accédé_à_la_DFGSM2_par": "Primant de PACES"
 },
 {
   "id": 282,
   "Vous_avez_accédé_à_la_DFGSM2_par": "Redoublant de PACES"
 },
 {
   "id": 283,
   "Vous_avez_accédé_à_la_DFGSM2_par": "PACES adaptée oral"
 },
 {
   "id": 284,
   "Vous_avez_accédé_à_la_DFGSM2_par": "Redoublant de PACES"
 },
 {
   "id": 285,
   "Vous_avez_accédé_à_la_DFGSM2_par": ""
 },
 {
   "id": 286,
   "Vous_avez_accédé_à_la_DFGSM2_par": ""
 },
 {
   "id": 287,
   "Vous_avez_accédé_à_la_DFGSM2_par": "PACES adaptée oral"
 },
 {
   "id": 288,
   "Vous_avez_accédé_à_la_DFGSM2_par": ""
 },
 {
   "id": 289,
   "Vous_avez_accédé_à_la_DFGSM2_par": "PACES adaptée écrit"
 },
 {
   "id": 290,
   "Vous_avez_accédé_à_la_DFGSM2_par": "Primant de PACES"
 },
 {
   "id": 291,
   "Vous_avez_accédé_à_la_DFGSM2_par": ""
 },
 {
   "id": 292,
   "Vous_avez_accédé_à_la_DFGSM2_par": "Redoublant de PACES"
 },
 {
   "id": 293,
   "Vous_avez_accédé_à_la_DFGSM2_par": "Redoublant de PACES"
 },
 {
   "id": 294,
   "Vous_avez_accédé_à_la_DFGSM2_par": ""
 },
 {
   "id": 295,
   "Vous_avez_accédé_à_la_DFGSM2_par": "Primant de PACES"
 },
 {
   "id": 296,
   "Vous_avez_accédé_à_la_DFGSM2_par": "Redoublant de PACES"
 },
 {
   "id": 297,
   "Vous_avez_accédé_à_la_DFGSM2_par": ""
 },
 {
   "id": 298,
   "Vous_avez_accédé_à_la_DFGSM2_par": "Primant de PACES"
 },
 {
   "id": 299,
   "Vous_avez_accédé_à_la_DFGSM2_par": "Primant de PACES"
 },
 {
   "id": 300,
   "Vous_avez_accédé_à_la_DFGSM2_par": "Primant de PACES"
 },
 {
   "id": 301,
   "Vous_avez_accédé_à_la_DFGSM2_par": "Passerelle"
 },
 {
   "id": 302,
   "Vous_avez_accédé_à_la_DFGSM2_par": "Primant de PACES"
 },
 {
   "id": 303,
   "Vous_avez_accédé_à_la_DFGSM2_par": ""
 },
 {
   "id": 304,
   "Vous_avez_accédé_à_la_DFGSM2_par": "Redoublant de PACES"
 },
 {
   "id": 305,
   "Vous_avez_accédé_à_la_DFGSM2_par": ""
 },
 {
   "id": 306,
   "Vous_avez_accédé_à_la_DFGSM2_par": ""
 },
 {
   "id": 307,
   "Vous_avez_accédé_à_la_DFGSM2_par": "Primant de PACES"
 },
 {
   "id": 308,
   "Vous_avez_accédé_à_la_DFGSM2_par": "Redoublant de PACES"
 },
 {
   "id": 309,
   "Vous_avez_accédé_à_la_DFGSM2_par": "Passerelle"
 },
 {
   "id": 310,
   "Vous_avez_accédé_à_la_DFGSM2_par": "Redoublant de PACES"
 },
 {
   "id": 311,
   "Vous_avez_accédé_à_la_DFGSM2_par": "Redoublant de PACES"
 },
 {
   "id": 312,
   "Vous_avez_accédé_à_la_DFGSM2_par": "Nouvelle-Calédonie / Luxembourg"
 },
 {
   "id": 313,
   "Vous_avez_accédé_à_la_DFGSM2_par": "Redoublant de PACES"
 },
 {
   "id": 314,
   "Vous_avez_accédé_à_la_DFGSM2_par": "Primant de PACES"
 },
 {
   "id": 315,
   "Vous_avez_accédé_à_la_DFGSM2_par": "Primant de PACES"
 },
 {
   "id": 316,
   "Vous_avez_accédé_à_la_DFGSM2_par": "Passerelle"
 },
 {
   "id": 317,
   "Vous_avez_accédé_à_la_DFGSM2_par": "Nouvelle-Calédonie / Luxembourg"
 },
 {
   "id": 318,
   "Vous_avez_accédé_à_la_DFGSM2_par": "Redoublant de PACES"
 },
 {
   "id": 319,
   "Vous_avez_accédé_à_la_DFGSM2_par": "Primant de PACES"
 },
 {
   "id": 320,
   "Vous_avez_accédé_à_la_DFGSM2_par": "Redoublant de PACES"
 },
 {
   "id": 321,
   "Vous_avez_accédé_à_la_DFGSM2_par": "Redoublant de PACES"
 },
 {
   "id": 322,
   "Vous_avez_accédé_à_la_DFGSM2_par": "Primant de PACES"
 },
 {
   "id": 323,
   "Vous_avez_accédé_à_la_DFGSM2_par": ""
 },
 {
   "id": 324,
   "Vous_avez_accédé_à_la_DFGSM2_par": "Primant de PACES"
 },
 {
   "id": 325,
   "Vous_avez_accédé_à_la_DFGSM2_par": "Nouvelle-Calédonie / Luxembourg"
 },
 {
   "id": 326,
   "Vous_avez_accédé_à_la_DFGSM2_par": "Primant de PACES"
 },
 {
   "id": 327,
   "Vous_avez_accédé_à_la_DFGSM2_par": ""
 },
 {
   "id": 328,
   "Vous_avez_accédé_à_la_DFGSM2_par": "PACES adaptée oral"
 },
 {
   "id": 329,
   "Vous_avez_accédé_à_la_DFGSM2_par": ""
 },
 {
   "id": 330,
   "Vous_avez_accédé_à_la_DFGSM2_par": "Primant de PACES"
 },
 {
   "id": 331,
   "Vous_avez_accédé_à_la_DFGSM2_par": "Primant de PACES"
 },
 {
   "id": 332,
   "Vous_avez_accédé_à_la_DFGSM2_par": "Redoublant de PACES"
 },
 {
   "id": 333,
   "Vous_avez_accédé_à_la_DFGSM2_par": "PACES adaptée écrit"
 },
 {
   "id": 334,
   "Vous_avez_accédé_à_la_DFGSM2_par": "Primant de PACES"
 },
 {
   "id": 335,
   "Vous_avez_accédé_à_la_DFGSM2_par": "Redoublant de PACES"
 },
 {
   "id": 336,
   "Vous_avez_accédé_à_la_DFGSM2_par": "Primant de PACES"
 },
 {
   "id": 337,
   "Vous_avez_accédé_à_la_DFGSM2_par": "Primant de PACES"
 },
 {
   "id": 338,
   "Vous_avez_accédé_à_la_DFGSM2_par": "Primant de PACES"
 },
 {
   "id": 339,
   "Vous_avez_accédé_à_la_DFGSM2_par": "Redoublant de PACES"
 },
 {
   "id": 340,
   "Vous_avez_accédé_à_la_DFGSM2_par": "Passerelle"
 },
 {
   "id": 341,
   "Vous_avez_accédé_à_la_DFGSM2_par": "Primant de PACES"
 },
 {
   "id": 342,
   "Vous_avez_accédé_à_la_DFGSM2_par": ""
 },
 {
   "id": 343,
   "Vous_avez_accédé_à_la_DFGSM2_par": "Primant de PACES"
 },
 {
   "id": 344,
   "Vous_avez_accédé_à_la_DFGSM2_par": "Redoublant de PACES"
 },
 {
   "id": 345,
   "Vous_avez_accédé_à_la_DFGSM2_par": "PACES adaptée écrit"
 },
 {
   "id": 346,
   "Vous_avez_accédé_à_la_DFGSM2_par": "Primant de PACES"
 },
 {
   "id": 347,
   "Vous_avez_accédé_à_la_DFGSM2_par": "PACES adaptée écrit"
 },
 {
   "id": 348,
   "Vous_avez_accédé_à_la_DFGSM2_par": ""
 },
 {
   "id": 349,
   "Vous_avez_accédé_à_la_DFGSM2_par": ""
 },
 {
   "id": 350,
   "Vous_avez_accédé_à_la_DFGSM2_par": ""
 },
 {
   "id": 351,
   "Vous_avez_accédé_à_la_DFGSM2_par": ""
 },
 {
   "id": 352,
   "Vous_avez_accédé_à_la_DFGSM2_par": "Primant de PACES"
 },
 {
   "id": 353,
   "Vous_avez_accédé_à_la_DFGSM2_par": ""
 },
 {
   "id": 354,
   "Vous_avez_accédé_à_la_DFGSM2_par": "Redoublant de PACES"
 },
 {
   "id": 355,
   "Vous_avez_accédé_à_la_DFGSM2_par": "Primant de PACES"
 },
 {
   "id": 356,
   "Vous_avez_accédé_à_la_DFGSM2_par": ""
 },
 {
   "id": 357,
   "Vous_avez_accédé_à_la_DFGSM2_par": "Primant de PACES"
 },
 {
   "id": 358,
   "Vous_avez_accédé_à_la_DFGSM2_par": "Primant de PACES"
 },
 {
   "id": 359,
   "Vous_avez_accédé_à_la_DFGSM2_par": "PACES adaptée écrit"
 },
 {
   "id": 360,
   "Vous_avez_accédé_à_la_DFGSM2_par": "Primant de PACES"
 },
 {
   "id": 361,
   "Vous_avez_accédé_à_la_DFGSM2_par": "Redoublant de PACES"
 },
 {
   "id": 362,
   "Vous_avez_accédé_à_la_DFGSM2_par": ""
 },
 {
   "id": 363,
   "Vous_avez_accédé_à_la_DFGSM2_par": "Redoublant de PACES"
 },
 {
   "id": 364,
   "Vous_avez_accédé_à_la_DFGSM2_par": ""
 },
 {
   "id": 365,
   "Vous_avez_accédé_à_la_DFGSM2_par": "Redoublant de PACES"
 },
 {
   "id": 366,
   "Vous_avez_accédé_à_la_DFGSM2_par": "Primant de PACES"
 },
 {
   "id": 367,
   "Vous_avez_accédé_à_la_DFGSM2_par": ""
 },
 {
   "id": 368,
   "Vous_avez_accédé_à_la_DFGSM2_par": "Redoublant de PACES"
 },
 {
   "id": 369,
   "Vous_avez_accédé_à_la_DFGSM2_par": ""
 },
 {
   "id": 370,
   "Vous_avez_accédé_à_la_DFGSM2_par": ""
 },
 {
   "id": 371,
   "Vous_avez_accédé_à_la_DFGSM2_par": "Primant de PACES"
 },
 {
   "id": 372,
   "Vous_avez_accédé_à_la_DFGSM2_par": ""
 },
 {
   "id": 373,
   "Vous_avez_accédé_à_la_DFGSM2_par": "Redoublant de PACES"
 },
 {
   "id": 374,
   "Vous_avez_accédé_à_la_DFGSM2_par": "Redoublant de PACES"
 },
 {
   "id": 375,
   "Vous_avez_accédé_à_la_DFGSM2_par": "Primant de PACES"
 },
 {
   "id": 376,
   "Vous_avez_accédé_à_la_DFGSM2_par": "Primant de PACES"
 },
 {
   "id": 377,
   "Vous_avez_accédé_à_la_DFGSM2_par": "Primant de PACES"
 },
 {
   "id": 378,
   "Vous_avez_accédé_à_la_DFGSM2_par": "PACES adaptée écrit"
 },
 {
   "id": 379,
   "Vous_avez_accédé_à_la_DFGSM2_par": "Primant de PACES"
 },
 {
   "id": 380,
   "Vous_avez_accédé_à_la_DFGSM2_par": "Redoublant de PACES"
 },
 {
   "id": 381,
   "Vous_avez_accédé_à_la_DFGSM2_par": "Redoublant de PACES"
 },
 {
   "id": 382,
   "Vous_avez_accédé_à_la_DFGSM2_par": "PACES adaptée écrit"
 },
 {
   "id": 383,
   "Vous_avez_accédé_à_la_DFGSM2_par": "Redoublant de PACES"
 },
 {
   "id": 384,
   "Vous_avez_accédé_à_la_DFGSM2_par": ""
 },
 {
   "id": 385,
   "Vous_avez_accédé_à_la_DFGSM2_par": "Redoublant de PACES"
 },
 {
   "id": 386,
   "Vous_avez_accédé_à_la_DFGSM2_par": ""
 },
 {
   "id": 387,
   "Vous_avez_accédé_à_la_DFGSM2_par": ""
 },
 {
   "id": 388,
   "Vous_avez_accédé_à_la_DFGSM2_par": "Primant de PACES"
 },
 {
   "id": 389,
   "Vous_avez_accédé_à_la_DFGSM2_par": "Redoublant de PACES"
 },
 {
   "id": 390,
   "Vous_avez_accédé_à_la_DFGSM2_par": "Primant de PACES"
 },
 {
   "id": 391,
   "Vous_avez_accédé_à_la_DFGSM2_par": "Primant de PACES"
 },
 {
   "id": 392,
   "Vous_avez_accédé_à_la_DFGSM2_par": "Nouvelle-Calédonie / Luxembourg"
 },
 {
   "id": 393,
   "Vous_avez_accédé_à_la_DFGSM2_par": "Primant de PACES"
 },
 {
   "id": 394,
   "Vous_avez_accédé_à_la_DFGSM2_par": "Primant de PACES"
 },
 {
   "id": 395,
   "Vous_avez_accédé_à_la_DFGSM2_par": "Redoublant de PACES"
 },
 {
   "id": 396,
   "Vous_avez_accédé_à_la_DFGSM2_par": "Redoublant de PACES"
 },
 {
   "id": 397,
   "Vous_avez_accédé_à_la_DFGSM2_par": "Primant de PACES"
 },
 {
   "id": 398,
   "Vous_avez_accédé_à_la_DFGSM2_par": "Primant de PACES"
 },
 {
   "id": 399,
   "Vous_avez_accédé_à_la_DFGSM2_par": "Redoublant de PACES"
 },
 {
   "id": 400,
   "Vous_avez_accédé_à_la_DFGSM2_par": "Primant de PACES"
 },
 {
   "id": 401,
   "Vous_avez_accédé_à_la_DFGSM2_par": "Redoublant de PACES"
 },
 {
   "id": 402,
   "Vous_avez_accédé_à_la_DFGSM2_par": "Redoublant de PACES"
 },
 {
   "id": 403,
   "Vous_avez_accédé_à_la_DFGSM2_par": "Redoublant de PACES"
 },
 {
   "id": 404,
   "Vous_avez_accédé_à_la_DFGSM2_par": "Primant de PACES"
 },
 {
   "id": 405,
   "Vous_avez_accédé_à_la_DFGSM2_par": ""
 },
 {
   "id": 406,
   "Vous_avez_accédé_à_la_DFGSM2_par": ""
 },
 {
   "id": 407,
   "Vous_avez_accédé_à_la_DFGSM2_par": ""
 },
 {
   "id": 408,
   "Vous_avez_accédé_à_la_DFGSM2_par": "PACES adaptée oral"
 },
 {
   "id": 409,
   "Vous_avez_accédé_à_la_DFGSM2_par": ""
 },
 {
   "id": 410,
   "Vous_avez_accédé_à_la_DFGSM2_par": "Redoublant de PACES"
 },
 {
   "id": 411,
   "Vous_avez_accédé_à_la_DFGSM2_par": "Redoublant de PACES"
 },
 {
   "id": 412,
   "Vous_avez_accédé_à_la_DFGSM2_par": ""
 },
 {
   "id": 413,
   "Vous_avez_accédé_à_la_DFGSM2_par": ""
 },
 {
   "id": 414,
   "Vous_avez_accédé_à_la_DFGSM2_par": "PACES adaptée écrit"
 },
 {
   "id": 415,
   "Vous_avez_accédé_à_la_DFGSM2_par": "Redoublant de PACES"
 },
 {
   "id": 416,
   "Vous_avez_accédé_à_la_DFGSM2_par": ""
 },
 {
   "id": 417,
   "Vous_avez_accédé_à_la_DFGSM2_par": "Primant de PACES"
 },
 {
   "id": 418,
   "Vous_avez_accédé_à_la_DFGSM2_par": "Primant de PACES"
 },
 {
   "id": 419,
   "Vous_avez_accédé_à_la_DFGSM2_par": "Primant de PACES"
 },
 {
   "id": 420,
   "Vous_avez_accédé_à_la_DFGSM2_par": "Passerelle"
 },
 {
   "id": 421,
   "Vous_avez_accédé_à_la_DFGSM2_par": "Primant de PACES"
 },
 {
   "id": 422,
   "Vous_avez_accédé_à_la_DFGSM2_par": "PACES adaptée écrit"
 }
]